<annotation>
	<folder>cat</folder>
	<filename>flickr_cat_000264.jpg</filename>
	<path>/Users/woolee/biases-are-features-dataset/afhq/data/afhq/train/cat/flickr_cat_000264.jpg</path>
	<source>
		<database>Unknown</database>
	</source>
	<size>
		<width>512</width>
		<height>512</height>
		<depth>3</depth>
	</size>
	<segmented>0</segmented>
	<object>
		<name>t</name>
		<pose>Unspecified</pose>
		<truncated>0</truncated>
		<difficult>0</difficult>
		<bndbox>
			<xmin>134</xmin>
			<ymin>113</ymin>
			<xmax>394</xmax>
			<ymax>238</ymax>
		</bndbox>
	</object>
</annotation>
